{
    "data": [
        {
            "index": "1",
            "name": "仓储业务管理",
            "level": 1,
            "menuData": [
                {
                    "index": "leaseRight",
                    "name": "租借权限管理",
                    "level": 2,
                }
            ]
        },
        {
            "index": "2",
            "name": "组织机构",
            "level": 1,
            "menuData": [
                {
                    "index": "user",
                    "name": "人员管理"
                },
                 {
                    "index": "orgnazition",
                    "name": "机构管理"
                },
                 {
                    "index": "role",
                    "name": "角色管理"
                },
                 {
                    "index": "permission",
                    "name": "权限管理"
                }
            ]
        }
    ]
}